open2fa/__init__.py
open2fa/cli.py
open2fa/cli_utils.py
open2fa/common.py
open2fa/config.py
open2fa/ex.py
open2fa/main.py
open2fa/msgs.py
open2fa/totp.py
open2fa/utils.py
open2fa/version.py
open2fa-1.4.6.dist-info/LICENSE
open2fa-1.4.6.dist-info/METADATA
open2fa-1.4.6.dist-info/WHEEL
open2fa-1.4.6.dist-info/entry_points.txt
open2fa-1.4.6.dist-info/top_level.txt
open2fa-1.4.6.dist-info/RECORD
