Metadata-Version: 2.1
Name: open2fa
Version: 1.4.6
Summary: A 2FA CLI tool for generating 2FA codes using TOTP secrets, with an optional SECURE remote api, and an optional web ui enabling 2FA code generation from any device
Author-email: Cary Carter <ccarterdev@gmail.com>
Project-URL: Homepage, https://open2fa.liberfy.ai
Project-URL: Repository, https://github.com/cc-d/open2fa
Project-URL: Issues, https://github.com/cc-d/open2fa/issues
Project-URL: Server, https://github.com/cc-d/open2fa-server
Project-URL: Documentation, https://github.com/cc-d/open2fa
Project-URL: Changelog, https://github.com/cc-d/open2fa/blob/main/CHANGELOG.md
Classifier: Programming Language :: Python :: 3
Classifier: Programming Language :: Python :: 3.7
Classifier: Programming Language :: Python :: 3.8
Classifier: Programming Language :: Python :: 3.9
Classifier: Programming Language :: Python :: 3.10
Classifier: Programming Language :: Python :: 3.11
Classifier: License :: OSI Approved :: MIT License
Classifier: Operating System :: OS Independent
Requires-Python: >=3.7
License-File: LICENSE
Requires-Dist: requests
Requires-Dist: logfunc <3
Requires-Dist: cryptography <42
Requires-Dist: pyshared <2
Requires-Dist: base58 ==2.1.1
Provides-Extra: dev
Requires-Dist: pytest ; extra == 'dev'
Requires-Dist: pytest-cov ; extra == 'dev'
Requires-Dist: pytest-xdist ; extra == 'dev'
Requires-Dist: pytest-html ; extra == 'dev'
Requires-Dist: black ; extra == 'dev'
Requires-Dist: isort ; extra == 'dev'
Requires-Dist: flake8 ; extra == 'dev'
Requires-Dist: twine ; extra == 'dev'
Requires-Dist: build ; extra == 'dev'
Requires-Dist: pyshared ; extra == 'dev'
